jadio_aitools/__init__.py
jadio_aitools/tools/api_doc.py
jadio_aitools/tools/backup_file.py
jadio_aitools/tools/backup_project.py
jadio_aitools/tools/check_bugs.py
jadio_aitools/tools/check_inbox.py
jadio_aitools/tools/code_search.py
jadio_aitools/tools/complexityreport.py
jadio_aitools/tools/converttomd.py
jadio_aitools/tools/converttopdf.py
jadio_aitools/tools/deadcode.py
jadio_aitools/tools/dependency_graph.py
jadio_aitools/tools/differentiator.py
jadio_aitools/tools/download_file.py
jadio_aitools/tools/encryptor.py
jadio_aitools/tools/extract_class.py
jadio_aitools/tools/file_count.py
jadio_aitools/tools/file_tree.py
jadio_aitools/tools/github.py
jadio_aitools/tools/godobjects.py
jadio_aitools/tools/googlesearch.py
jadio_aitools/tools/greentext_parser.py
jadio_aitools/tools/hasher.py
jadio_aitools/tools/huggingfacemodels.py
jadio_aitools/tools/imagewindow.py
jadio_aitools/tools/lint.py
jadio_aitools/tools/list_todos.py
jadio_aitools/tools/localhost.py
jadio_aitools/tools/localport_manage.py
jadio_aitools/tools/logbook.py
jadio_aitools/tools/method_indexer.py
jadio_aitools/tools/monitor.py
jadio_aitools/tools/password_manager.py
jadio_aitools/tools/process_killer.py
jadio_aitools/tools/recallmemory.py
jadio_aitools/tools/refactor.py
jadio_aitools/tools/report_bugs.py
jadio_aitools/tools/send_email.py
jadio_aitools/tools/setupvenv.py
jadio_aitools/tools/storememory.py
jadio_aitools/tools/supercanvas.py
jadio_aitools/tools/symbol_indexer.py
jadio_aitools/tools/temporary_canvas.py
jadio_aitools/tools/temporary_instructions.py
jadio_aitools/tools/temporary_notepad.py
jadio_aitools/tools/temporary_server.py
jadio_aitools/tools/watchai.py
jadio_aitools/tools/create/account_creation.py
jadio_aitools/tools/create/create_css_file.py
jadio_aitools/tools/create/create_gitignore_file.py
jadio_aitools/tools/create/create_html_file.py
jadio_aitools/tools/create/create_javascript_file.py
jadio_aitools/tools/create/create_json_file.py
jadio_aitools-0.0.1.dist-info/METADATA
jadio_aitools-0.0.1.dist-info/WHEEL
jadio_aitools-0.0.1.dist-info/licenses/LICENSE
jadio_aitools-0.0.1.dist-info/RECORD
