Metadata-Version: 2.4
Name: jadio-aitools
Version: 0.0.1
Summary: Jadio-compatible extension package
License-Expression: MIT
License-File: LICENSE
Requires-Python: >=3.8
Requires-Dist: jadio>=0.0.2
